gitin/__init__.py
gitin/__version__.py
gitin/gitin.py
gitin-0.1.0.dist-info/LICENSE
gitin-0.1.0.dist-info/METADATA
gitin-0.1.0.dist-info/WHEEL
gitin-0.1.0.dist-info/entry_points.txt
gitin-0.1.0.dist-info/top_level.txt
gitin-0.1.0.dist-info/RECORD
