Metadata-Version: 2.1
Name: gitin
Version: 0.1.0
Summary: Extract and format GitHub repository content for LLMs
Home-page: https://github.com/unclecode/gitin
Author: unclecode
Author-email: 
Project-URL: Bug Tracker, https://github.com/unclecode/gitin/issues
Project-URL: Documentation, https://github.com/unclecode/gitin#readme
Project-URL: Source Code, https://github.com/unclecode/gitin
Project-URL: Changelog, https://github.com/unclecode/gitin/blob/main/CHANGELOG.md
Keywords: github,llm,content-extraction,markdown,repository-analysis
Classifier: Development Status :: 4 - Beta
Classifier: Environment :: Console
Classifier: Intended Audience :: Developers
Classifier: Intended Audience :: Science/Research
Classifier: License :: OSI Approved :: MIT License
Classifier: Operating System :: OS Independent
Classifier: Programming Language :: Python :: 3
Classifier: Programming Language :: Python :: 3.6
Classifier: Programming Language :: Python :: 3.7
Classifier: Programming Language :: Python :: 3.8
Classifier: Programming Language :: Python :: 3.9
Classifier: Programming Language :: Python :: 3.10
Classifier: Topic :: Software Development :: Libraries :: Python Modules
Classifier: Topic :: Software Development :: Version Control :: Git
Classifier: Topic :: Text Processing :: Markup :: Markdown
Requires-Python: >=3.6
License-File: LICENSE
Requires-Dist: click>=8.1.7
Requires-Dist: requests>=2.31.0
Requires-Dist: tqdm>=4.66.1
